pytools3/__MainLib__.py
pytools3/__init__.py
pytools3/__main__.py
pytools3/docs.py
pytools3/pytprompt.py
pytoolskar-0.0.3.dist-info/LICENSE.txt
pytoolskar-0.0.3.dist-info/METADATA
pytoolskar-0.0.3.dist-info/WHEEL
pytoolskar-0.0.3.dist-info/top_level.txt
pytoolskar-0.0.3.dist-info/RECORD
